wsheatzypy/__init__.py
wsheatzypy/auth.py
wsheatzypy/const.py
wsheatzypy/exception.py
wsheatzypy/heatzy.py
wsheatzypy/websocket.py
wsheatzypy-1.2.3.dist-info/LICENSE
wsheatzypy-1.2.3.dist-info/METADATA
wsheatzypy-1.2.3.dist-info/WHEEL
wsheatzypy-1.2.3.dist-info/top_level.txt
wsheatzypy-1.2.3.dist-info/RECORD
